mysql_basics/__init__.py
mysql_basics/main.py
mysql_basics-0.1.0.dist-info/METADATA
mysql_basics-0.1.0.dist-info/WHEEL
mysql_basics-0.1.0.dist-info/top_level.txt
mysql_basics-0.1.0.dist-info/RECORD
