Metadata-Version: 2.1
Name: mysql_basics
Version: 0.1.0
Summary: A module for mysql to get some basic details of database and tables like table ddl and row cound and space usage.
Author: Harish Daga
Requires-Python: >=3.6
Requires-Dist: boto3 ==1.34.154
Requires-Dist: botocore ==1.34.154
Requires-Dist: certifi ==2024.7.4
Requires-Dist: charset-normalizer ==3.3.2
Requires-Dist: docutils ==0.21.2
Requires-Dist: idna ==3.7
Requires-Dist: importlib-metadata ==8.2.0
Requires-Dist: jaraco.classes ==3.4.0
Requires-Dist: jaraco.context ==5.3.0
Requires-Dist: jaraco.functools ==4.0.2
Requires-Dist: jmespath ==1.0.1
Requires-Dist: keyring ==25.3.0
Requires-Dist: markdown-it-py ==3.0.0
Requires-Dist: mdurl ==0.1.2
Requires-Dist: more-itertools ==10.3.0
Requires-Dist: mysql-connector-python ==9.0.0
Requires-Dist: mysql-basics ==0.0.0
Requires-Dist: nh3 ==0.2.18
Requires-Dist: numpy ==2.0.1
Requires-Dist: pandas ==2.2.2
Requires-Dist: pkginfo ==1.10.0
Requires-Dist: Pygments ==2.18.0
Requires-Dist: Pyment ==0.3.3
Requires-Dist: python-dateutil ==2.9.0.post0
Requires-Dist: pytz ==2024.1
Requires-Dist: readme-renderer ==44.0
Requires-Dist: requests ==2.32.3
Requires-Dist: requests-toolbelt ==1.0.0
Requires-Dist: rfc3986 ==2.0.0
Requires-Dist: rich ==13.7.1
Requires-Dist: s3transfer ==0.10.2
Requires-Dist: setuptools ==72.1.0
Requires-Dist: six ==1.16.0
Requires-Dist: twine ==5.1.1
Requires-Dist: tzdata ==2024.1
Requires-Dist: urllib3 ==2.2.2
Requires-Dist: zipp ==3.19.2
